utilities_nlp/__init__.py
utilities_nlp/arial-bold-italic.ttf
utilities_nlp/arial-bold.ttf
utilities_nlp/arial-italic.ttf
utilities_nlp/arial.ttf
utilities_nlp/courier-new.ttf
utilities_nlp/utilities_nlp.py
utilities_nlp/verdana-bold-italic.ttf
utilities_nlp/verdana-bold.ttf
utilities_nlp/verdana-italic.ttf
utilities_nlp/verdana.ttf
utilities_nlp/upscale/__init__.py
utilities_nlp/upscale/config.json
utilities_nlp/upscale/pytorch_model_4x.pt
utilities_nlp-6.0.2.dist-info/LICENSE.txt
utilities_nlp-6.0.2.dist-info/METADATA
utilities_nlp-6.0.2.dist-info/WHEEL
utilities_nlp-6.0.2.dist-info/top_level.txt
utilities_nlp-6.0.2.dist-info/RECORD
