Metadata-Version: 2.2
Name: utilities_nlp
Version: 6.0.2
Home-page: https://github.com/sapiens-technology/utilities_nlp
Author: SAPIENS TECHNOLOGY
License: Proprietary Software
License-File: LICENSE.txt
Requires-Dist: TTS==0.22.0
Requires-Dist: sapiens-transformers
Requires-Dist: sapiens-infinite-context-window
Requires-Dist: paddleocr==2.7.3
Requires-Dist: paddlepaddle
Requires-Dist: pillow
Requires-Dist: cloudinary
Requires-Dist: count-tokens
Requires-Dist: tiktoken
Requires-Dist: opencv-python
Requires-Dist: opencv-python-headless
Requires-Dist: ffmpeg-python
Requires-Dist: gTTS
Requires-Dist: pydub
Requires-Dist: noisereduce
Requires-Dist: yt-dlp
Requires-Dist: httpx<0.28.0
Requires-Dist: youtube-search-python
Requires-Dist: youtube-transcript-api
Requires-Dist: moviepy
Requires-Dist: certifi
Requires-Dist: beautifulsoup4
Requires-Dist: numpy
Requires-Dist: fasttext
Requires-Dist: langid
Requires-Dist: langdetect
Requires-Dist: requests
Requires-Dist: mutagen
Requires-Dist: openai-whisper
Requires-Dist: setuptools-rust
Requires-Dist: fpdf
Requires-Dist: reportlab
Requires-Dist: python-docx
Requires-Dist: docx
Requires-Dist: openpyxl
Requires-Dist: pandas
Requires-Dist: XlsxWriter
Requires-Dist: python-pptx
Requires-Dist: matplotlib
Requires-Dist: seaborn
Requires-Dist: graphviz
Requires-Dist: networkx
Requires-Dist: wordcloud
Requires-Dist: rembg
Requires-Dist: onnxruntime
Requires-Dist: super-image
Requires-Dist: huggingface-hub
Dynamic: author
Dynamic: home-page
Dynamic: license
Dynamic: requires-dist
